asyncapi3/__init__.py
asyncapi3/models/__init__.py
asyncapi3/models/asyncapi.py
asyncapi3/models/base.py
asyncapi3/models/base_models.py
asyncapi3/models/channel.py
asyncapi3/models/components.py
asyncapi3/models/helpers.py
asyncapi3/models/info.py
asyncapi3/models/message.py
asyncapi3/models/operation.py
asyncapi3/models/schema.py
asyncapi3/models/security.py
asyncapi3/models/server.py
asyncapi3/models/bindings/__init__.py
asyncapi3/models/bindings/amqp.py
asyncapi3/models/bindings/amqp1.py
asyncapi3/models/bindings/anypointmq.py
asyncapi3/models/bindings/core.py
asyncapi3/models/bindings/googlepubsub.py
asyncapi3/models/bindings/http.py
asyncapi3/models/bindings/ibmmq.py
asyncapi3/models/bindings/jms.py
asyncapi3/models/bindings/kafka.py
asyncapi3/models/bindings/mercure.py
asyncapi3/models/bindings/mqtt.py
asyncapi3/models/bindings/mqtt5.py
asyncapi3/models/bindings/nats.py
asyncapi3/models/bindings/pulsar.py
asyncapi3/models/bindings/redis.py
asyncapi3/models/bindings/sns.py
asyncapi3/models/bindings/solace.py
asyncapi3/models/bindings/sqs.py
asyncapi3/models/bindings/stomp.py
asyncapi3/models/bindings/websockets.py
asyncapi3-0.0.2.dist-info/METADATA
asyncapi3-0.0.2.dist-info/WHEEL
asyncapi3-0.0.2.dist-info/licenses/LICENSE
asyncapi3-0.0.2.dist-info/RECORD
