Metadata-Version: 2.4
Name: asyncapi3
Version: 0.0.2
Summary: Python AsyncAPI 3.0 object model
Project-URL: Repository, https://github.com/insspb/asyncapi3
Project-URL: Issues, https://github.com/insspb/asyncapi3/issues
Author: Andrey Shpak
Maintainer: Andrey Shpak
License: Apache-2.0
License-File: LICENSE
Classifier: Development Status :: 3 - Alpha
Classifier: Framework :: Pydantic
Classifier: Framework :: Pydantic :: 2
Classifier: Intended Audience :: Developers
Classifier: License :: OSI Approved :: Apache Software License
Classifier: Operating System :: OS Independent
Classifier: Programming Language :: Python :: 3
Classifier: Programming Language :: Python :: 3 :: Only
Classifier: Programming Language :: Python :: 3.10
Classifier: Programming Language :: Python :: 3.11
Classifier: Programming Language :: Python :: 3.12
Classifier: Programming Language :: Python :: 3.13
Classifier: Programming Language :: Python :: 3.14
Classifier: Topic :: Software Development :: Libraries :: Python Modules
Classifier: Typing :: Typed
Requires-Python: >=3.10
Requires-Dist: pyaml>=25.7.0
Requires-Dist: pydantic>=2.12.5
